{
  "main": {
    "id": "cc1de8783c2e6640",
    "type": "split",
    "children": [
      {
        "id": "6e0e3a5fc8ece16b",
        "type": "tabs",
        "children": [
          {
            "id": "ea0ee9c61b2e6c32",
            "type": "leaf",
            "state": {
              "type": "empty",
              "state": {},
              "icon": "lucide-file",
              "title": "New tab"
            }
          }
        ]
      }
    ],
    "direction": "vertical"
  },
  "left": {
    "id": "74b368207150563c",
    "type": "split",
    "children": [
      {
        "id": "14019b21102edd56",
        "type": "tabs",
        "children": [
          {
            "id": "604ad4795954ad32",
            "type": "leaf",
            "state": {
              "type": "file-explorer",
              "state": {
                "sortOrder": "alphabetical",
                "autoReveal": false
              },
              "icon": "lucide-folder-closed",
              "title": "Files"
            }
          },
          {
            "id": "ab74607f3cfbafd9",
            "type": "leaf",
            "state": {
              "type": "search",
              "state": {
                "query": "",
                "matchingCase": false,
                "explainSearch": false,
                "collapseAll": false,
                "extraContext": false,
                "sortOrder": "alphabetical"
              },
              "icon": "lucide-search",
              "title": "Search"
            }
          },
          {
            "id": "c43a33277f8f9818",
            "type": "leaf",
            "state": {
              "type": "bookmarks",
              "state": {},
              "icon": "lucide-bookmark",
              "title": "Bookmarks"
            }
          }
        ]
      }
    ],
    "direction": "horizontal",
    "width": 300
  },
  "right": {
    "id": "95b4081dc03d9912",
    "type": "split",
    "children": [
      {
        "id": "d498efc2703a3123",
        "type": "tabs",
        "children": [
          {
            "id": "5fb799b2c096f790",
            "type": "leaf",
            "state": {
              "type": "backlink",
              "state": {
                "file": "Culture Tree.canvas",
                "collapseAll": false,
                "extraContext": false,
                "sortOrder": "alphabetical",
                "showSearch": false,
                "searchQuery": "",
                "backlinkCollapsed": false,
                "unlinkedCollapsed": true
              },
              "icon": "links-coming-in",
              "title": "Backlinks for Culture Tree"
            }
          },
          {
            "id": "7675d0c2fdf3ad7e",
            "type": "leaf",
            "state": {
              "type": "outgoing-link",
              "state": {
                "file": "Culture Tree.canvas",
                "linksCollapsed": false,
                "unlinkedCollapsed": true
              },
              "icon": "links-going-out",
              "title": "Outgoing links from Culture Tree"
            }
          },
          {
            "id": "c21234e16d178211",
            "type": "leaf",
            "state": {
              "type": "tag",
              "state": {
                "sortOrder": "frequency",
                "useHierarchy": true,
                "showSearch": false,
                "searchQuery": ""
              },
              "icon": "lucide-tags",
              "title": "Tags"
            }
          },
          {
            "id": "3e5d05ba19ac93da",
            "type": "leaf",
            "state": {
              "type": "outline",
              "state": {
                "file": "Culture Tree.canvas",
                "followCursor": false,
                "showSearch": false,
                "searchQuery": ""
              },
              "icon": "lucide-list",
              "title": "Outline of Culture Tree"
            }
          }
        ]
      }
    ],
    "direction": "horizontal",
    "width": 300,
    "collapsed": true
  },
  "left-ribbon": {
    "hiddenItems": {
      "switcher:Open quick switcher": false,
      "graph:Open graph view": false,
      "canvas:Create new canvas": false,
      "daily-notes:Open today's daily note": false,
      "templates:Insert template": false,
      "command-palette:Open command palette": false
    }
  },
  "active": "ea0ee9c61b2e6c32",
  "lastOpenFiles": [
    "Culture Tree.canvas",
    "Language Tree.canvas",
    "desktop.ini",
    "Untitled 1.md",
    "Untitled.md",
    "Welcome.md"
  ]
}